{
  "data": {
    "averageCompleteTime": 592.0,
    "subjectList": [
      {
        "id": "3646",
        "version": 0,
        "type": 1,
        "title": "关于open()函数的参数,下列描述正确的是?",
        "optionA": "\"w+\" 以十六进制格式打开一个文件只用于写入",
        "optionB": "\"r+\"打开一个文件用于读写.文件指针将会放在文件的末尾",
        "optionC": "\"w\" 打开一个文件只用于写入.如果该文件已存在则打开文件,并从原有位置开始编辑,即保留原有内容.如果该文件不存在,创建新文件",
        "optionD": "\"r\" 以只读方式打开文件,文件的指针将会放在文件的开头",
        "answer": "D",
        "analyzeContent": "\"w+\" 打开一个文件用于读写. \"r+\"打开一个文件用于读写.文件指针将会放在文件的开头. \"w\" 打开一个文件只用于写入.如果该文件已存在则打开文件,并从开头开始编辑,即原有内容会被删除.如果该文件不存在,创建新文件. \"r\" 以只读方式打开文件,文件的指针将会放在文件的开头.",
        "examDots": "12,",
        "difficultyLevel": "2",
        "weType": 0,
        "isMySubject": 0,
        "knowledgeNames": "核心内置函数",
        "answerStatus": 0,
        "compileEnvironment": 0
      },
      {
        "id": "3647",
        "version": 2,
        "type": 1,
        "title": "如下图代码,请问两条红线处应该填入?",
        "optionA": "1,没有变化 2,没有变化",
        "optionB": "1,没有变化 2,顺序会有变化",
        "optionC": "1,顺序会有变化 2,顺序会有变化",
        "optionD": "1,顺序会有变化 2,没有变化",
        "answer": "B",
        "analyzeContent": "考查学生对列表的sort函数以及sorted函数的掌握与理解.",
        "examDots": "12,",
        "difficultyLevel": "2",
        "weType": 0,
        "isMySubject": 0,
        "knowledgeNames": "核心内置函数",
        "answerStatus": 0,
        "compileEnvironment": 0
      },
      {
        "id": "3648",
        "version": 0,
        "type": 1,
        "title": "下面不同数制数据中,数值最大的是?",
        "optionA": "0x2B",
        "optionB": "0o37",
        "optionC": "41",
        "optionD": "0b100111",
        "answer": "A",
        "analyzeContent": "",
        "examDots": "12,",
        "difficultyLevel": "2",
        "weType": 0,
        "isMySubject": 0,
        "knowledgeNames": "编码,数制",
        "answerStatus": 0,
        "compileEnvironment": 0
      },
      {
        "id": "3649",
        "version": 0,
        "type": 1,
        "title": "执行下面代码:print(bool(2)+3)打印出的结果为?",
        "optionA": "3",
        "optionB": "4",
        "optionC": "5",
        "optionD": "报错",
        "answer": "B",
        "analyzeContent": "bool函数是int子类型,如果有参数,会返回true也就是整数1,所以正确答案是选项B,也就是数字4",
        "examDots": "12,",
        "difficultyLevel": "2",
        "weType": 0,
        "isMySubject": 0,
        "knowledgeNames": "核心内置函数",
        "answerStatus": 0,
        "compileEnvironment": 0
      },
      {
        "id": "3650",
        "version": 0,
        "type": 1,
        "title": "求既是 3 的倍数且各个位上的数的和是 8 的倍数的三位数,适合的算法是?",
        "optionA": "解析算法",
        "optionB": "枚举算法",
        "optionC": "排序算法",
        "optionD": "对分查找法",
        "answer": "B",
        "analyzeContent": "本题适合用枚举算法.",
        "examDots": "12,",
        "difficultyLevel": "2",
        "weType": 0,
        "isMySubject": 0,
        "knowledgeNames": "枚举算法",
        "answerStatus": 0,
        "compileEnvironment": 0
      },
      {
        "id": "3651",
        "version": 0,
        "type": 1,
        "title": "下列选项不是 Python 异常处理可能用到的关键字?",
        "optionA": "try",
        "optionB": "else",
        "optionC": "if",
        "optionD": "finally",
        "answer": "C",
        "analyzeContent": "本知识点是学习异常处理基本语句用法",
        "examDots": "12,",
        "difficultyLevel": "2",
        "weType": 0,
        "isMySubject": 0,
        "knowledgeNames": "异常处理",
        "answerStatus": 0,
        "compileEnvironment": 0
      },
      {
        "id": "3652",
        "version": 0,
        "type": 1,
        "title": "已定义学期末考核科目 km=[\" 语文 \",\" 数学 \",\" 英语 \"] ,先根据安排需要添加综合学科进入考试科目,操作正确的是?",
        "optionA": "km.append(\" 综合 \")",
        "optionB": "km.insert(\" 综合 \")",
        "optionC": "km.write(\" 综合 \")",
        "optionD": "km.read(\" 综合 \")",
        "answer": "A",
        "analyzeContent": "km.append(\"综合\") 使用append()对一维数据进行添加",
        "examDots": "12,",
        "difficultyLevel": "2",
        "weType": 0,
        "isMySubject": 0,
        "knowledgeNames": "核心内置函数",
        "answerStatus": 0,
        "compileEnvironment": 0
      },
      {
        "id": "3653",
        "version": 0,
        "type": 1,
        "title": "表达式chr(ord(\"0\")+3)的结果是?",
        "optionA": "333",
        "optionB": "'3'",
        "optionC": "\"000\"",
        "optionD": "\"0\",\"0\",\"0\"",
        "answer": "B",
        "analyzeContent": "ord()函数主要用来返回对应字符的ascii码,chr()主要用来表示ascii码对应的字符,chr(ord(\"0\")+3)的值为'3'",
        "examDots": "12,",
        "difficultyLevel": "2",
        "weType": 0,
        "isMySubject": 0,
        "knowledgeNames": "核心内置函数",
        "answerStatus": 0,
        "compileEnvironment": 0
      },
      {
        "id": "3654",
        "version": 0,
        "type": 1,
        "title": "与十进制数 1770 对应的八进制数是?",
        "optionA": "3350",
        "optionB": "3351",
        "optionC": "3352",
        "optionD": "3540",
        "answer": "C",
        "analyzeContent": "反向取余法 3352",
        "examDots": "12,",
        "difficultyLevel": "2",
        "weType": 0,
        "isMySubject": 0,
        "knowledgeNames": "编码,数制",
        "answerStatus": 0,
        "compileEnvironment": 0
      },
      {
        "id": "3655",
        "version": 0,
        "type": 1,
        "title": "下面代码的输出结果是? a = [5,1,3,4] print(sorted(a,reverse = True))",
        "optionA": "[5, 1, 3, 4]",
        "optionB": "[5, 4, 3, 1]",
        "optionC": "[4, 3, 1, 5]",
        "optionD": "[1, 3, 4, 5]",
        "answer": "B",
        "analyzeContent": "对列表进行降序排序",
        "examDots": "12,",
        "difficultyLevel": "2",
        "weType": 0,
        "isMySubject": 0,
        "knowledgeNames": "列表",
        "answerStatus": 0,
        "compileEnvironment": 0
      },
      {
        "id": "3656",
        "version": 0,
        "type": 1,
        "title": "用冒泡排序算法对 6 个数进行排序,进行比较的次数为?",
        "optionA": "4",
        "optionB": "5",
        "optionC": "10",
        "optionD": "15",
        "answer": "D",
        "analyzeContent": "6 个数进行冒泡排序,比较次数为 5+4+3+2+1",
        "examDots": "12,",
        "difficultyLevel": "2",
        "weType": 0,
        "isMySubject": 0,
        "knowledgeNames": "冒泡算法",
        "answerStatus": 0,
        "compileEnvironment": 0
      },
      {
        "id": "3657",
        "version": 0,
        "type": 1,
        "title": "以下代码执行后,如果用户输入为:3*6,则输出为?( ) cal=input(\"请输入计算公式:\\n\") print(eval(cal))",
        "optionA": "3*6",
        "optionB": "\"3*6\"",
        "optionC": "18",
        "optionD": "\"18\"",
        "answer": "C",
        "analyzeContent": "本题考查eval实现的功能,就是将字符串表达式进行运算,得到运算结果.",
        "examDots": "12,",
        "difficultyLevel": "2",
        "weType": 0,
        "isMySubject": 0,
        "knowledgeNames": "核心内置函数",
        "answerStatus": 0,
        "compileEnvironment": 0
      },
      {
        "id": "3658",
        "version": 0,
        "type": 1,
        "title": "关于 Python 函数的描述,正确的是?",
        "optionA": "表达式 float(\"3.14\") 的结果是 3.14",
        "optionB": "表达式 type(100) 的结果是十进制数",
        "optionC": "表达式 oct(100) 可以获得十六进制数",
        "optionD": "表达式 hex(100) 可以获得八进制数",
        "answer": "A",
        "analyzeContent": "选项 A 正确,选项 B.type(100) 的结果是,选项 C.oct(100) 的值是 '0o144' ,获得八进制数,选项 D.hex(100) 的值是 '0x64' ,获得十六进制数.",
        "examDots": "12,",
        "difficultyLevel": "2",
        "weType": 0,
        "isMySubject": 0,
        "knowledgeNames": "核心内置函数",
        "answerStatus": 0,
        "compileEnvironment": 0
      },
      {
        "id": "3659",
        "version": 0,
        "type": 1,
        "title": "Python中abs ()函数的作用为?",
        "optionA": "求绝对值",
        "optionB": "求开方结果",
        "optionC": "求平方结果",
        "optionD": "求立方结果",
        "answer": "A",
        "analyzeContent": "记住即可,abs就是求绝对值.",
        "examDots": "12,",
        "difficultyLevel": "2",
        "weType": 0,
        "isMySubject": 0,
        "knowledgeNames": "核心内置函数",
        "answerStatus": 0,
        "compileEnvironment": 0
      },
      {
        "id": "3660",
        "version": 0,
        "type": 1,
        "title": "以下代码的执行结果为? t=(11,25,36) avg=sum(t)/len(t) print(avg)",
        "optionA": "24",
        "optionB": "24.0",
        "optionC": "12",
        "optionD": "12.0",
        "answer": "B",
        "analyzeContent": "sum是求和函数,len是计数函数.两者相除就是就平均数,结果为小数.故有(11+25+36)/3等于24.0.",
        "examDots": "12,",
        "difficultyLevel": "2",
        "weType": 0,
        "isMySubject": 0,
        "knowledgeNames": "核心内置函数",
        "answerStatus": 0,
        "compileEnvironment": 0
      },
      {
        "id": "3661",
        "version": 0,
        "type": 1,
        "title": "Python 中十六进制与十进制进行转换时,下列表述错误的是?",
        "optionA": "十进制数 57 转换成十六进制,可以表示成 int('57',16)",
        "optionB": "十进制数 57 转换成十六进制,可以表示成 hex(57)",
        "optionC": "十六进制数 39 转换成十进制,可以表示成 int('39',16)",
        "optionD": "十六进制数 39 转换成十进制,可以表示成 0x39",
        "answer": "A",
        "analyzeContent": "",
        "examDots": "12,",
        "difficultyLevel": "2",
        "weType": 0,
        "isMySubject": 0,
        "knowledgeNames": "编码,数制",
        "answerStatus": 0,
        "compileEnvironment": 0
      },
      {
        "id": "3662",
        "version": 0,
        "type": 1,
        "title": "Python 中使用 open() 函数打开文件完成读的功能,下列说法错误的是?",
        "optionA": "readlines() 方法是读取文本所有的行 , 直到文件末尾",
        "optionB": "readline() 方法是读取文件的第一行",
        "optionC": "在同一个程序中,多次使用 readline() 方法后,程序仍读取第一行的内容",
        "optionD": "执行 readline() 方法后,运行的结果不是列表,而是字符串",
        "answer": "C",
        "analyzeContent": "",
        "examDots": "12,",
        "difficultyLevel": "2",
        "weType": 0,
        "isMySubject": 0,
        "knowledgeNames": "文件和数据处理",
        "answerStatus": 0,
        "compileEnvironment": 0
      },
      {
        "id": "3663",
        "version": 0,
        "type": 1,
        "title": "以下代码执行后,得到的结果为? list1 = [5, 0, 6, 1, 2, 7, 3, 4] print(sorted(list1, reverse=True))",
        "optionA": "[7, 6, 5, 4, 3, 2, 1, 0]",
        "optionB": "[0, 1, 2, 3, 4, 5, 6, 7]",
        "optionC": "[4, 3, 7, 2, 1, 6, 0, 5]",
        "optionD": "[5, 0, 6, 1, 2, 7, 3, 4]",
        "answer": "A",
        "analyzeContent": "从代码可知,程序实现功能为从大到小排序,所以结果为 A",
        "examDots": "12,",
        "difficultyLevel": "2",
        "weType": 0,
        "isMySubject": 0,
        "knowledgeNames": "直接插入排序",
        "answerStatus": 0,
        "compileEnvironment": 0
      },
      {
        "id": "3664",
        "version": 0,
        "type": 1,
        "title": "int(7.8)的执行结果是?",
        "optionA": "8",
        "optionB": "8.0",
        "optionC": "7",
        "optionD": "7.0",
        "answer": "C",
        "analyzeContent": "int只是去掉小数部分,所以结果为7",
        "examDots": "12,",
        "difficultyLevel": "2",
        "weType": 0,
        "isMySubject": 0,
        "knowledgeNames": "核心内置函数",
        "answerStatus": 0,
        "compileEnvironment": 0
      },
      {
        "id": "3665",
        "version": 0,
        "type": 1,
        "title": "关于查找的说法,下列说法正确的是?",
        "optionA": "顺序查找属于无序查找",
        "optionB": "对分查找一定能找到数据",
        "optionC": "对分查找是一种低效的查找方法",
        "optionD": "顺序查找次数一定比对分查找次数多",
        "answer": "A",
        "analyzeContent": "顺序查找和对分不一定能查找到数据.对分查找是一种高效的查找方法.如果数据元素在第一个位置,顺序查找次数不一定比对分查找次数多.",
        "examDots": "12,",
        "difficultyLevel": "2",
        "weType": 0,
        "isMySubject": 0,
        "knowledgeNames": "算法基础",
        "answerStatus": 0,
        "compileEnvironment": 0
      },
      {
        "id": "3666",
        "version": 0,
        "type": 1,
        "title": "当 try 子句中没有任何错误时,一定不会执行语句?",
        "optionA": "try",
        "optionB": "else",
        "optionC": "except",
        "optionD": "finally",
        "answer": "C",
        "analyzeContent": "本试题考察异常处理中的语句用法",
        "examDots": "12,",
        "difficultyLevel": "2",
        "weType": 0,
        "isMySubject": 0,
        "knowledgeNames": "异常处理",
        "answerStatus": 0,
        "compileEnvironment": 0
      },
      {
        "id": "3667",
        "version": 0,
        "type": 1,
        "title": "Python 可以通过哪个函数实现字符串数据的格式化处理?",
        "optionA": "format",
        "optionB": "int",
        "optionC": "max",
        "optionD": "str",
        "answer": "A",
        "analyzeContent": "python 中, format() 函数实现字符串数据的格式化处理.",
        "examDots": "12,",
        "difficultyLevel": "2",
        "weType": 0,
        "isMySubject": 0,
        "knowledgeNames": "核心内置函数",
        "answerStatus": 0,
        "compileEnvironment": 0
      },
      {
        "id": "3668",
        "version": 0,
        "type": 1,
        "title": "以下代码的输出结果是? ls =[] for m in ' 想念 ': for n in ' 家人 ': ls.append(m+n) print(ls)",
        "optionA": "想念家人",
        "optionB": "想想念念家家人人",
        "optionC": "想家想人念家念人",
        "optionD": "[' 想家 ', ' 想人 ',' 念家 ',' 念人 ']",
        "answer": "D",
        "analyzeContent": "双循环读取数据存放到列表 ls 中,最后输出结果.",
        "examDots": "12,",
        "difficultyLevel": "2",
        "weType": 0,
        "isMySubject": 0,
        "knowledgeNames": "循环",
        "answerStatus": 0,
        "compileEnvironment": 0
      },
      {
        "id": "3669",
        "version": 0,
        "type": 1,
        "title": "format 方法通常用来格式化 print 的输出格式.以下程序中使用 format 来输出: 我叫小明 , 我今年 12 岁了 , 则代码中缺失部分应该填写? name=\" 小明 \" age=12 print(\" 我叫 {}, 我今年 {} 岁了 \".format(_________________))",
        "optionA": "age,name",
        "optionB": "name,age",
        "optionC": "name:age",
        "optionD": "age name",
        "answer": "B",
        "analyzeContent": "此题比较简单,就是考查字符串 format 拼接.函数参数,前后对应,逗号隔开即可.",
        "examDots": "12,",
        "difficultyLevel": "2",
        "weType": 0,
        "isMySubject": 0,
        "knowledgeNames": "核心内置函数",
        "answerStatus": 0,
        "compileEnvironment": 0
      },
      {
        "id": "3670",
        "version": 0,
        "type": 1,
        "title": "下列数据中,不可能表示十六进制数的是?",
        "optionA": "ABC",
        "optionB": "17F",
        "optionC": "8H5",
        "optionD": "9a01",
        "answer": "C",
        "analyzeContent": "",
        "examDots": "12,",
        "difficultyLevel": "2",
        "weType": 0,
        "isMySubject": 0,
        "knowledgeNames": "编码,数制",
        "answerStatus": 0,
        "compileEnvironment": 0
      },
      {
        "id": "3671",
        "version": 0,
        "type": 3,
        "title": "except 语句可以有多个, Python 会按 except 语句的顺序依次匹配你指定的异常.",
        "answer": "1",
        "analyzeContent": "except 语句可以有多个, Python 会按 except 语句的顺序依次匹配你指定的异常,如果异常已经处理就不会再进入后面的 except 语句.",
        "examDots": "12,",
        "weType": 0,
        "isMySubject": 0,
        "answerStatus": 0,
        "compileEnvironment": 0
      },
      {
        "id": "3672",
        "version": 0,
        "type": 3,
        "title": "any([]) 函数和 any(()) 函数的结果是 False .",
        "answer": "1",
        "analyzeContent": "any() 函数用于判断给定的可迭代参数 iterable 是否全部为 False ,则返回 False ,如果有一个为 True ,则返回 True .元素除了是 0 ,空, FALSE 外都算 TRUE .",
        "examDots": "12,",
        "weType": 0,
        "isMySubject": 0,
        "answerStatus": 0,
        "compileEnvironment": 0
      },
      {
        "id": "3673",
        "version": 0,
        "type": 3,
        "title": "利用 Python3 自带的 csv 库进行操作,可使用以下程序获取 class.csv 文件中存储的表头信息,并进行输出. import csv with open('class.csv') as f: reader=csv.reader(f) head_row=next(reader) print(head_row)",
        "answer": "1",
        "analyzeContent": "import csv with open('class.csv') as f: reader=csv.reader(f) head_row=next(reader) print(head_row) 利用 csv 库进行文件读取,通过变量读取表头信息并逐项打印",
        "examDots": "12,",
        "weType": 0,
        "isMySubject": 0,
        "answerStatus": 0,
        "compileEnvironment": 0
      },
      {
        "id": "3674",
        "version": 0,
        "type": 3,
        "title": "利用 csv 格式存储二维数据时,每行都是一个一维数据,用逗号分隔,可以有空行.",
        "answer": "0",
        "analyzeContent": "利用 csv 格式存储二维数据时,每行都是一个一维数据,用逗号分隔,不能有空行",
        "examDots": "12,",
        "weType": 0,
        "isMySubject": 0,
        "answerStatus": 0,
        "compileEnvironment": 0
      },
      {
        "id": "3675",
        "version": 1,
        "type": 3,
        "title": "数学老师对小明说:我要计算 [4,6,3,2,5,8,7,9] 这几个整数的平方,你能帮我编程实现吗? 小明说:两行代码就能实现.程序如下! 请判断,小明的这个程序是否正确.",
        "answer": "1",
        "analyzeContent": "本题综合考查学生对 list ()与 map ()函数的掌握情况.答案是正确.",
        "examDots": "12,",
        "weType": 0,
        "isMySubject": 0,
        "answerStatus": 0,
        "compileEnvironment": 0
      },
      {
        "id": "3676",
        "version": 0,
        "type": 3,
        "title": "多次使用 readline() 读取文件,如果要退到文件的起始位置,可以使用 seek() 实现.",
        "answer": "1",
        "examDots": "12,",
        "weType": 0,
        "isMySubject": 0,
        "answerStatus": 0,
        "compileEnvironment": 0
      },
      {
        "id": "3677",
        "version": 0,
        "type": 3,
        "title": "Python 中使用 print 函数输出时,输出完毕默认会换行,不能通过修改参数改为其它间隔方式.",
        "optionA": "",
        "optionB": "",
        "optionC": "",
        "optionD": "",
        "answer": "0",
        "analyzeContent": "print 函数中使用 end 参数可以指定换行之外的其它间隔符,如 Tab 等.",
        "examDots": "12,",
        "difficultyLevel": "1",
        "weType": 0,
        "isMySubject": 0,
        "knowledgeNames": "print()函数",
        "answerStatus": 0,
        "compileEnvironment": 0
      },
      {
        "id": "3678",
        "version": 0,
        "type": 3,
        "title": "十六进制与八进制数值之间的转换,常常借助二进制或者十进制作为中间的桥梁.",
        "optionA": "",
        "optionB": "",
        "optionC": "",
        "optionD": "",
        "answer": "1",
        "analyzeContent": "",
        "examDots": "12,",
        "difficultyLevel": "2",
        "weType": 0,
        "isMySubject": 0,
        "knowledgeNames": "编码,数制",
        "answerStatus": 0,
        "compileEnvironment": 0
      },
      {
        "id": "3679",
        "version": 0,
        "type": 3,
        "title": "同一个整数分别用十六进制和八进制表示后,数值一定不相等.",
        "optionA": "",
        "optionB": "",
        "optionC": "",
        "optionD": "",
        "answer": "0",
        "analyzeContent": "",
        "examDots": "12,",
        "difficultyLevel": "2",
        "weType": 0,
        "isMySubject": 0,
        "knowledgeNames": "编码,数制",
        "answerStatus": 0,
        "compileEnvironment": 0
      },
      {
        "id": "3680",
        "version": 0,
        "type": 3,
        "title": "语句 print(\"a\",\"b\",\"c\",sep=\" , \") 的输出结果是: \"a\" \"b\" \"c\" .",
        "optionA": "",
        "optionB": "",
        "optionC": "",
        "optionD": "",
        "answer": "0",
        "analyzeContent": "print(\"a\",\"b\",\"c\",sep=\" , \") 的结果是 a , b , c",
        "examDots": "12,",
        "difficultyLevel": "2",
        "weType": 0,
        "isMySubject": 0,
        "knowledgeNames": "print()函数",
        "answerStatus": 0,
        "compileEnvironment": 0
      },
      {
        "id": "3681",
        "version": 2,
        "type": 4,
        "title": "法定节假日是根据各国,各名族的风俗习惯或纪念要求,由国家法律统一规定的用以进行庆祝及度假的休息时间. 法定节假日制度是国家政治,经济,文化制度的重要反映,涉及经济社会的多个方面,涉及广大人民群众的切身利益.法定节假日的休假安排,为居民出行购物和休闲提供了时间上的便利,为拉动内需,促进经济增长做出了积极贡献. 给出一个 2020 年的节假日的放假日期 CSV 文件 (vacations.csv) ,内容示例如下 : 以第1行为例,1230表示12月30日,0101表示1月1日. 代码功能为: 读入CSV文件中数据,获得用户输入.根据用户输入的节假日名称,输出此节假日的假期范围.请补全代码. fi=open(\" /data/① \",\"r\") ls=[] for line in fi: ls.append(line.strip(\"\\n\").split(\",\")) fi.close() s=input(\"请输入节假日名称:\") for line in ls: if ② : print(\"{}的假期位于{}-{}之间\".format(line[1], line[2], line[3]))",
        "answer": "<br><p class=\"MsoNormal\"><span><font face=\"宋体\">① &nbsp;&nbsp;</font><font face=\"Calibri\">vacations.csv &nbsp;&nbsp;</font><font face=\"宋体\">(</font><font face=\"Calibri\">2</font><font face=\"宋体\">分)</font></span><span><o:p></o:p></span></p><p class=\"MsoNormal\"><span><font face=\"宋体\">② &nbsp;&nbsp;</font><font face=\"Calibri\">s == line[1] &nbsp;&nbsp;&nbsp;&nbsp;</font><font face=\"宋体\">(</font><font face=\"Calibri\">2</font><font face=\"宋体\">分)</font></span></p>",
        "analyzeContent": "fi=open(\"vacations.csv\",\"r\") ls=[] for line in fi: ls.append(line.strip(\"\\n\").split(\",\")) fi.close() s=input(\" 请输入节假日名称 :\") for line in ls: if s == line[1]: print(\"{} 的假期位于 {}-{} 之间 \".format(line[1], line[2], line[3]))",
        "examDots": "12,",
        "weType": 0,
        "isMySubject": 0,
        "answerStatus": 0,
        "compileEnvironment": 0
      },
      {
        "id": "3682",
        "version": 0,
        "type": 4,
        "title": "尊老王国有一个默认规则,排队必须遵守年长的在前,年幼的在后.一支正要出城的队伍,请帮助他们顺利出城. 输入: 15 , 78 , 96 , 45 , 36 输出 [96, 78, 45, 36, 15] [3, 2, 4, 5, 1] 请在划线处补全代码,实现以上功能 s = input() x= s.split(' , ') a = [] b = [] n = 0 for i in range(0, len(x)): a.append(int(x[i])) n = ___________ b.append(n) for i in range(n-1): for j in range(i+1, n): if (__________): _________________ b[i], b[j] = b[j], b[i] print(a) print(b)",
        "answer": "<p class=\"MsoNormal\"><span><font face=\"宋体\">① </font><font face=\"Calibri\">n+1(5</font><font face=\"宋体\">分</font><font face=\"Calibri\">)</font></span><span><o:p></o:p></span></p><p class=\"MsoNormal\"><span><font face=\"宋体\">② </font><font face=\"Calibri\">a[i] &lt;a[j]</font><font face=\"宋体\">(</font><font face=\"Calibri\">5</font><font face=\"宋体\">分)</font></span><span><o:p></o:p></span></p><p class=\"MsoNormal\"><span><font face=\"宋体\">③ </font><font face=\"Calibri\">a[i], a[j] = a[j], a[i]</font><font face=\"宋体\">(</font><font face=\"Calibri\">6</font><font face=\"宋体\">分)</font></span></p>",
        "analyzeContent": "s = input() x= s.split(' , ') a = [] b = [] n = 0 for i in range(0, len(x)): a.append(int(x[i])) n = n + 1 b.append(n) for i in range(n-1): for j in range(i+1, n): if (a[i] <a[j]): a[i], a[j] = a[j], a[i] b[i], b[j] = b[j], b[i] print(a) print(b)",
        "examDots": "12,",
        "weType": 0,
        "isMySubject": 0,
        "answerStatus": 0,
        "compileEnvironment": 0
      },
      {
        "id": "3683",
        "version": 0,
        "type": 4,
        "title": "有 n 个人围成一圈,顺序排号.从第一个人开始报数(从 1 到 3 报数),凡报到 3 的人退出圈子,问最后留下的是原来第几号的那位. n = int(input(' 请输入总人数 :')) num = [] for i in range(n): num.append( ① ) i = 0 k = 0 m = 0 while m < n - 1: if ② : k += 1 if k == 3: num[i] = 0 k = 0 ③ i += 1 if i == n : i = 0 i = 0 while num[i] == 0:i += 1 print( ④ )",
        "answer": "<p class=\"MsoNormal\"><span><font face=\"宋体\">① &nbsp;&nbsp;</font><font face=\"Calibri\">i + 1 &nbsp;&nbsp;&nbsp;&nbsp;&nbsp;&nbsp;&nbsp;&nbsp;&nbsp;&nbsp;&nbsp;</font><font face=\"宋体\">(</font><font face=\"Calibri\">3</font><font face=\"宋体\">分)</font></span><span><o:p></o:p></span></p><p class=\"MsoNormal\"><span><font face=\"宋体\">② &nbsp;</font><font face=\"Calibri\">num[i] != 0 &nbsp;&nbsp;</font><font face=\"宋体\">(</font><font face=\"Calibri\">2</font><font face=\"宋体\">分)</font></span><span><o:p></o:p></span></p><p class=\"MsoNormal\"><span><font face=\"宋体\">③ &nbsp;&nbsp;</font><font face=\"Calibri\">m += 1 &nbsp;&nbsp;&nbsp;&nbsp;&nbsp;&nbsp;&nbsp;</font><font face=\"宋体\">(</font><font face=\"Calibri\">3</font><font face=\"宋体\">分)</font></span><span><o:p></o:p></span></p><p class=\"MsoNormal\"><span><font face=\"宋体\">④ &nbsp;&nbsp;</font><font face=\"Calibri\">num[i] &nbsp;&nbsp;&nbsp;&nbsp;&nbsp;&nbsp;&nbsp;&nbsp;</font><font face=\"宋体\">(</font><font face=\"Calibri\">2</font><font face=\"宋体\">分)</font></span><span><o:p></o:p></span></p>",
        "analyzeContent": "n = int(input(' 请输入总人数 :')) num = [] for i in range(n): num.append(i + 1) i = 0 k = 0 m = 0 while m < n - 1: if num[i] != 0 : k += 1 if k == 3: num[i] = 0 k = 0 m += 1 i += 1 if i == n : i = 0 i = 0 while num[i] == 0:i += 1 print(num[i])",
        "examDots": "12,",
        "weType": 0,
        "isMySubject": 0,
        "answerStatus": 0,
        "compileEnvironment": 0
      }
    ],
    "calculatePercentage": 0.0,
    "completeTime": "1",
    "answerScore": 0.0,
    "title": "202106Python三级真题",
    "averageScore": 14
  },
  "code": 200,
  "msg": "操作成功"
}